getserv/__init__.py
getserv/__main__.py
getserv/drivers/__init__.py
getserv/drivers/base_driver.py
getserv/drivers/digitalocean_driver.py
getserv-0.0.4.dist-info/LICENSE
getserv-0.0.4.dist-info/METADATA
getserv-0.0.4.dist-info/WHEEL
getserv-0.0.4.dist-info/entry_points.txt
getserv-0.0.4.dist-info/top_level.txt
getserv-0.0.4.dist-info/RECORD
