Metadata-Version: 2.1
Name: getserv
Version: 0.0.4
Summary: Retrieve a stable server to deploy
Home-page: https://github.com/davideperozzi/getserv
Author: Davide Perozzi
Author-email: myself@davideperozzi.com
License: UNKNOWN
Platform: UNKNOWN
Classifier: Programming Language :: Python :: 3
Classifier: License :: OSI Approved :: MIT License
Classifier: Operating System :: OS Independent
Requires-Python: >=3.6
